<?xml version="1.0" encoding="UTF-8"?>
<data>
	<node>
		<id><![CDATA[22]]></id>
		<title><![CDATA[ffff]]></title>
		<content><![CDATA[test]]></content>
		<excerpt><![CDATA[]]></excerpt>
		<date><![CDATA[2020-11-11]]></date>
		<posttype><![CDATA[mm365_companies]]></posttype>
		<permalink><![CDATA[http://localhost/mmsdc/company/ffff/]]></permalink>
		<imageurl><![CDATA[]]></imageurl>
		<imagetitle><![CDATA[]]></imagetitle>
		<imagecaption><![CDATA[]]></imagecaption>
		<imagedescription><![CDATA[]]></imagedescription>
		<imagealttext><![CDATA[]]></imagealttext>
		<imagefeatured><![CDATA[]]></imagefeatured>
		<attachmenturl><![CDATA[]]></attachmenturl>
		<categories><![CDATA[]]></categories>
		<status><![CDATA[published]]></status>
		<authorid><![CDATA[1]]></authorid>
		<authorusername><![CDATA[mmsdc]]></authorusername>
		<authoremail><![CDATA[rakeshmr@v2soft.com]]></authoremail>
		<authorfirstname><![CDATA[]]></authorfirstname>
		<authorlastname><![CDATA[]]></authorlastname>
		<slug><![CDATA[ffff]]></slug>
		<format><![CDATA[]]></format>
		<template><![CDATA[]]></template>
		<parent><![CDATA[0]]></parent>
		<parentslug><![CDATA[0]]></parentslug>
		<order><![CDATA[0]]></order>
		<commentstatus><![CDATA[closed]]></commentstatus>
		<pingstatus><![CDATA[closed]]></pingstatus>
		<postmodifieddate><![CDATA[2020-11-11]]></postmodifieddate>
	</node>
	<node>
		<id><![CDATA[264]]></id>
		<title><![CDATA[Hello]]></title>
		<content><![CDATA[]]></content>
		<excerpt><![CDATA[]]></excerpt>
		<date><![CDATA[2020-12-04]]></date>
		<posttype><![CDATA[mm365_companies]]></posttype>
		<permalink><![CDATA[http://localhost/mmsdc/company/hello/]]></permalink>
		<imageurl><![CDATA[]]></imageurl>
		<imagetitle><![CDATA[]]></imagetitle>
		<imagecaption><![CDATA[]]></imagecaption>
		<imagedescription><![CDATA[]]></imagedescription>
		<imagealttext><![CDATA[]]></imagealttext>
		<imagefeatured><![CDATA[]]></imagefeatured>
		<attachmenturl><![CDATA[]]></attachmenturl>
		<categories><![CDATA[]]></categories>
		<status><![CDATA[published]]></status>
		<authorid><![CDATA[3]]></authorid>
		<authorusername><![CDATA[magna_john]]></authorusername>
		<authoremail><![CDATA[john@magna.kom]]></authoremail>
		<authorfirstname><![CDATA[John]]></authorfirstname>
		<authorlastname><![CDATA[Doe]]></authorlastname>
		<slug><![CDATA[hello]]></slug>
		<format><![CDATA[]]></format>
		<template><![CDATA[]]></template>
		<parent><![CDATA[0]]></parent>
		<parentslug><![CDATA[0]]></parentslug>
		<order><![CDATA[0]]></order>
		<commentstatus><![CDATA[closed]]></commentstatus>
		<pingstatus><![CDATA[closed]]></pingstatus>
		<postmodifieddate><![CDATA[2020-12-04]]></postmodifieddate>
	</node>
	<node>
		<id><![CDATA[287]]></id>
		<title><![CDATA[Micro Biosystems CSA]]></title>
		<content><![CDATA[]]></content>
		<excerpt><![CDATA[]]></excerpt>
		<date><![CDATA[2020-12-10]]></date>
		<posttype><![CDATA[mm365_companies]]></posttype>
		<permalink><![CDATA[http://localhost/mmsdc/company/micro-biosystems/]]></permalink>
		<imageurl><![CDATA[]]></imageurl>
		<imagetitle><![CDATA[]]></imagetitle>
		<imagecaption><![CDATA[]]></imagecaption>
		<imagedescription><![CDATA[]]></imagedescription>
		<imagealttext><![CDATA[]]></imagealttext>
		<imagefeatured><![CDATA[]]></imagefeatured>
		<attachmenturl><![CDATA[]]></attachmenturl>
		<categories><![CDATA[]]></categories>
		<status><![CDATA[publish]]></status>
		<authorid><![CDATA[3]]></authorid>
		<authorusername><![CDATA[magna_john]]></authorusername>
		<authoremail><![CDATA[john@magna.kom]]></authoremail>
		<authorfirstname><![CDATA[John]]></authorfirstname>
		<authorlastname><![CDATA[Doe]]></authorlastname>
		<slug><![CDATA[micro-biosystems]]></slug>
		<format><![CDATA[]]></format>
		<template><![CDATA[]]></template>
		<parent><![CDATA[0]]></parent>
		<parentslug><![CDATA[0]]></parentslug>
		<order><![CDATA[0]]></order>
		<commentstatus><![CDATA[closed]]></commentstatus>
		<pingstatus><![CDATA[closed]]></pingstatus>
		<postmodifieddate><![CDATA[2020-12-23]]></postmodifieddate>
	</node>
	<node>
		<id><![CDATA[329]]></id>
		<title><![CDATA[SOLDER DE MEXICO, S.A. DE C.V]]></title>
		<content><![CDATA[]]></content>
		<excerpt><![CDATA[]]></excerpt>
		<date><![CDATA[2020-12-17]]></date>
		<posttype><![CDATA[mm365_companies]]></posttype>
		<permalink><![CDATA[http://localhost/mmsdc/company/solder-de-mexico-s-a-de-c-v/]]></permalink>
		<imageurl><![CDATA[]]></imageurl>
		<imagetitle><![CDATA[]]></imagetitle>
		<imagecaption><![CDATA[]]></imagecaption>
		<imagedescription><![CDATA[]]></imagedescription>
		<imagealttext><![CDATA[]]></imagealttext>
		<imagefeatured><![CDATA[]]></imagefeatured>
		<attachmenturl><![CDATA[]]></attachmenturl>
		<categories><![CDATA[]]></categories>
		<status><![CDATA[publish]]></status>
		<authorid><![CDATA[6]]></authorid>
		<authorusername><![CDATA[gruposolder]]></authorusername>
		<authoremail><![CDATA[contacto@gruposolder.com.mx]]></authoremail>
		<authorfirstname><![CDATA[SOLDER DE MEXICO]]></authorfirstname>
		<authorlastname><![CDATA[S.A. DE C.V]]></authorlastname>
		<slug><![CDATA[solder-de-mexico-s-a-de-c-v]]></slug>
		<format><![CDATA[]]></format>
		<template><![CDATA[]]></template>
		<parent><![CDATA[0]]></parent>
		<parentslug><![CDATA[0]]></parentslug>
		<order><![CDATA[0]]></order>
		<commentstatus><![CDATA[closed]]></commentstatus>
		<pingstatus><![CDATA[closed]]></pingstatus>
		<postmodifieddate><![CDATA[2020-12-28]]></postmodifieddate>
	</node>
	<node>
		<id><![CDATA[330]]></id>
		<title><![CDATA[TEXILES LEON, S.A. DE C.V.]]></title>
		<content><![CDATA[]]></content>
		<excerpt><![CDATA[]]></excerpt>
		<date><![CDATA[2020-12-17]]></date>
		<posttype><![CDATA[mm365_companies]]></posttype>
		<permalink><![CDATA[http://localhost/mmsdc/company/texiles-leon-s-a-de-c-v/]]></permalink>
		<imageurl><![CDATA[]]></imageurl>
		<imagetitle><![CDATA[]]></imagetitle>
		<imagecaption><![CDATA[]]></imagecaption>
		<imagedescription><![CDATA[]]></imagedescription>
		<imagealttext><![CDATA[]]></imagealttext>
		<imagefeatured><![CDATA[]]></imagefeatured>
		<attachmenturl><![CDATA[]]></attachmenturl>
		<categories><![CDATA[]]></categories>
		<status><![CDATA[publish]]></status>
		<authorid><![CDATA[7]]></authorid>
		<authorusername><![CDATA[textilesleon]]></authorusername>
		<authoremail><![CDATA[mbello@textilesleon.com]]></authoremail>
		<authorfirstname><![CDATA[TEXILES]]></authorfirstname>
		<authorlastname><![CDATA[LEON]]></authorlastname>
		<slug><![CDATA[texiles-leon-s-a-de-c-v]]></slug>
		<format><![CDATA[]]></format>
		<template><![CDATA[]]></template>
		<parent><![CDATA[0]]></parent>
		<parentslug><![CDATA[0]]></parentslug>
		<order><![CDATA[0]]></order>
		<commentstatus><![CDATA[closed]]></commentstatus>
		<pingstatus><![CDATA[closed]]></pingstatus>
		<postmodifieddate><![CDATA[2020-12-23]]></postmodifieddate>
	</node>
	<node>
		<id><![CDATA[363]]></id>
		<title><![CDATA[Fabric Leon]]></title>
		<content><![CDATA[]]></content>
		<excerpt><![CDATA[]]></excerpt>
		<date><![CDATA[2020-12-24]]></date>
		<posttype><![CDATA[mm365_companies]]></posttype>
		<permalink><![CDATA[http://localhost/mmsdc/company/fabric-leon/]]></permalink>
		<imageurl><![CDATA[]]></imageurl>
		<imagetitle><![CDATA[]]></imagetitle>
		<imagecaption><![CDATA[]]></imagecaption>
		<imagedescription><![CDATA[]]></imagedescription>
		<imagealttext><![CDATA[]]></imagealttext>
		<imagefeatured><![CDATA[]]></imagefeatured>
		<attachmenturl><![CDATA[]]></attachmenturl>
		<categories><![CDATA[]]></categories>
		<status><![CDATA[publish]]></status>
		<authorid><![CDATA[8]]></authorid>
		<authorusername><![CDATA[fabric]]></authorusername>
		<authoremail><![CDATA[fabric@leon.com]]></authoremail>
		<authorfirstname><![CDATA[Fabric]]></authorfirstname>
		<authorlastname><![CDATA[Leon]]></authorlastname>
		<slug><![CDATA[fabric-leon]]></slug>
		<format><![CDATA[]]></format>
		<template><![CDATA[]]></template>
		<parent><![CDATA[0]]></parent>
		<parentslug><![CDATA[0]]></parentslug>
		<order><![CDATA[0]]></order>
		<commentstatus><![CDATA[closed]]></commentstatus>
		<pingstatus><![CDATA[closed]]></pingstatus>
		<postmodifieddate><![CDATA[2020-12-24]]></postmodifieddate>
	</node>
	<node>
		<id><![CDATA[366]]></id>
		<title><![CDATA[Fabtech Mexico Ltd]]></title>
		<content><![CDATA[]]></content>
		<excerpt><![CDATA[]]></excerpt>
		<date><![CDATA[2020-12-24]]></date>
		<posttype><![CDATA[mm365_companies]]></posttype>
		<permalink><![CDATA[http://localhost/mmsdc/company/fabtech-mexico-ltd/]]></permalink>
		<imageurl><![CDATA[]]></imageurl>
		<imagetitle><![CDATA[]]></imagetitle>
		<imagecaption><![CDATA[]]></imagecaption>
		<imagedescription><![CDATA[]]></imagedescription>
		<imagealttext><![CDATA[]]></imagealttext>
		<imagefeatured><![CDATA[]]></imagefeatured>
		<attachmenturl><![CDATA[]]></attachmenturl>
		<categories><![CDATA[]]></categories>
		<status><![CDATA[publish]]></status>
		<authorid><![CDATA[9]]></authorid>
		<authorusername><![CDATA[fabmexico]]></authorusername>
		<authoremail><![CDATA[fabmex@fbmex.com]]></authoremail>
		<authorfirstname><![CDATA[Fabtech]]></authorfirstname>
		<authorlastname><![CDATA[Mexico]]></authorlastname>
		<slug><![CDATA[fabtech-mexico-ltd]]></slug>
		<format><![CDATA[]]></format>
		<template><![CDATA[]]></template>
		<parent><![CDATA[0]]></parent>
		<parentslug><![CDATA[0]]></parentslug>
		<order><![CDATA[0]]></order>
		<commentstatus><![CDATA[closed]]></commentstatus>
		<pingstatus><![CDATA[closed]]></pingstatus>
		<postmodifieddate><![CDATA[2020-12-24]]></postmodifieddate>
	</node>
	<node>
		<id><![CDATA[368]]></id>
		<title><![CDATA[Warpwaste]]></title>
		<content><![CDATA[]]></content>
		<excerpt><![CDATA[]]></excerpt>
		<date><![CDATA[2020-12-24]]></date>
		<posttype><![CDATA[mm365_companies]]></posttype>
		<permalink><![CDATA[http://localhost/mmsdc/company/warpwaste/]]></permalink>
		<imageurl><![CDATA[]]></imageurl>
		<imagetitle><![CDATA[]]></imagetitle>
		<imagecaption><![CDATA[]]></imagecaption>
		<imagedescription><![CDATA[]]></imagedescription>
		<imagealttext><![CDATA[]]></imagealttext>
		<imagefeatured><![CDATA[]]></imagefeatured>
		<attachmenturl><![CDATA[]]></attachmenturl>
		<categories><![CDATA[]]></categories>
		<status><![CDATA[publish]]></status>
		<authorid><![CDATA[10]]></authorid>
		<authorusername><![CDATA[warpwaste]]></authorusername>
		<authoremail><![CDATA[wastemanager@gmail.com]]></authoremail>
		<authorfirstname><![CDATA[Warp]]></authorfirstname>
		<authorlastname><![CDATA[Waste]]></authorlastname>
		<slug><![CDATA[warpwaste]]></slug>
		<format><![CDATA[]]></format>
		<template><![CDATA[]]></template>
		<parent><![CDATA[0]]></parent>
		<parentslug><![CDATA[0]]></parentslug>
		<order><![CDATA[0]]></order>
		<commentstatus><![CDATA[closed]]></commentstatus>
		<pingstatus><![CDATA[closed]]></pingstatus>
		<postmodifieddate><![CDATA[2020-12-29]]></postmodifieddate>
	</node>
	<node>
		<id><![CDATA[376]]></id>
		<title><![CDATA[Dummy Kalashinkov Aero Staffing]]></title>
		<content><![CDATA[]]></content>
		<excerpt><![CDATA[]]></excerpt>
		<date><![CDATA[2020-12-28]]></date>
		<posttype><![CDATA[mm365_companies]]></posttype>
		<permalink><![CDATA[http://localhost/mmsdc/company/376/]]></permalink>
		<imageurl><![CDATA[]]></imageurl>
		<imagetitle><![CDATA[]]></imagetitle>
		<imagecaption><![CDATA[]]></imagecaption>
		<imagedescription><![CDATA[]]></imagedescription>
		<imagealttext><![CDATA[]]></imagealttext>
		<imagefeatured><![CDATA[]]></imagefeatured>
		<attachmenturl><![CDATA[]]></attachmenturl>
		<categories><![CDATA[]]></categories>
		<status><![CDATA[publish]]></status>
		<authorid><![CDATA[1]]></authorid>
		<authorusername><![CDATA[mmsdc]]></authorusername>
		<authoremail><![CDATA[rakeshmr@v2soft.com]]></authoremail>
		<authorfirstname><![CDATA[]]></authorfirstname>
		<authorlastname><![CDATA[]]></authorlastname>
		<slug><![CDATA[376]]></slug>
		<format><![CDATA[]]></format>
		<template><![CDATA[]]></template>
		<parent><![CDATA[0]]></parent>
		<parentslug><![CDATA[0]]></parentslug>
		<order><![CDATA[0]]></order>
		<commentstatus><![CDATA[closed]]></commentstatus>
		<pingstatus><![CDATA[closed]]></pingstatus>
		<postmodifieddate><![CDATA[2020-12-29]]></postmodifieddate>
	</node>
	<node>
		<id><![CDATA[380]]></id>
		<title><![CDATA[Dummy Neil Amstrong Aero Staffing]]></title>
		<content><![CDATA[]]></content>
		<excerpt><![CDATA[]]></excerpt>
		<date><![CDATA[2020-12-29]]></date>
		<posttype><![CDATA[mm365_companies]]></posttype>
		<permalink><![CDATA[http://localhost/mmsdc/company/dummy-neil-amstrong-aero-staffing/]]></permalink>
		<imageurl><![CDATA[]]></imageurl>
		<imagetitle><![CDATA[]]></imagetitle>
		<imagecaption><![CDATA[]]></imagecaption>
		<imagedescription><![CDATA[]]></imagedescription>
		<imagealttext><![CDATA[]]></imagealttext>
		<imagefeatured><![CDATA[]]></imagefeatured>
		<attachmenturl><![CDATA[]]></attachmenturl>
		<categories><![CDATA[]]></categories>
		<status><![CDATA[publish]]></status>
		<authorid><![CDATA[1]]></authorid>
		<authorusername><![CDATA[mmsdc]]></authorusername>
		<authoremail><![CDATA[rakeshmr@v2soft.com]]></authoremail>
		<authorfirstname><![CDATA[]]></authorfirstname>
		<authorlastname><![CDATA[]]></authorlastname>
		<slug><![CDATA[dummy-neil-amstrong-aero-staffing]]></slug>
		<format><![CDATA[]]></format>
		<template><![CDATA[]]></template>
		<parent><![CDATA[0]]></parent>
		<parentslug><![CDATA[0]]></parentslug>
		<order><![CDATA[0]]></order>
		<commentstatus><![CDATA[closed]]></commentstatus>
		<pingstatus><![CDATA[closed]]></pingstatus>
		<postmodifieddate><![CDATA[2020-12-29]]></postmodifieddate>
	</node>
	<node>
		<id><![CDATA[383]]></id>
		<title><![CDATA[Mexican Federation of Aerospace Industries]]></title>
		<content><![CDATA[]]></content>
		<excerpt><![CDATA[]]></excerpt>
		<date><![CDATA[2020-12-29]]></date>
		<posttype><![CDATA[mm365_companies]]></posttype>
		<permalink><![CDATA[http://localhost/mmsdc/company/mexican-federation-of-aerospace-industries/]]></permalink>
		<imageurl><![CDATA[]]></imageurl>
		<imagetitle><![CDATA[]]></imagetitle>
		<imagecaption><![CDATA[]]></imagecaption>
		<imagedescription><![CDATA[]]></imagedescription>
		<imagealttext><![CDATA[]]></imagealttext>
		<imagefeatured><![CDATA[]]></imagefeatured>
		<attachmenturl><![CDATA[]]></attachmenturl>
		<categories><![CDATA[]]></categories>
		<status><![CDATA[publish]]></status>
		<authorid><![CDATA[11]]></authorid>
		<authorusername><![CDATA[mexaero]]></authorusername>
		<authoremail><![CDATA[mexaero@gmail.com]]></authoremail>
		<authorfirstname><![CDATA[Mexican Federation]]></authorfirstname>
		<authorlastname><![CDATA[of Aerospace Industries]]></authorlastname>
		<slug><![CDATA[mexican-federation-of-aerospace-industries]]></slug>
		<format><![CDATA[]]></format>
		<template><![CDATA[]]></template>
		<parent><![CDATA[0]]></parent>
		<parentslug><![CDATA[0]]></parentslug>
		<order><![CDATA[0]]></order>
		<commentstatus><![CDATA[closed]]></commentstatus>
		<pingstatus><![CDATA[closed]]></pingstatus>
		<postmodifieddate><![CDATA[2020-12-29]]></postmodifieddate>
	</node>
	<node>
		<id><![CDATA[387]]></id>
		<title><![CDATA[Gmail Company]]></title>
		<content><![CDATA[]]></content>
		<excerpt><![CDATA[]]></excerpt>
		<date><![CDATA[2020-12-31]]></date>
		<posttype><![CDATA[mm365_companies]]></posttype>
		<permalink><![CDATA[http://localhost/mmsdc/company/gmail-company/]]></permalink>
		<imageurl><![CDATA[]]></imageurl>
		<imagetitle><![CDATA[]]></imagetitle>
		<imagecaption><![CDATA[]]></imagecaption>
		<imagedescription><![CDATA[]]></imagedescription>
		<imagealttext><![CDATA[]]></imagealttext>
		<imagefeatured><![CDATA[]]></imagefeatured>
		<attachmenturl><![CDATA[]]></attachmenturl>
		<categories><![CDATA[]]></categories>
		<status><![CDATA[publish]]></status>
		<authorid><![CDATA[12]]></authorid>
		<authorusername><![CDATA[testeracc]]></authorusername>
		<authoremail><![CDATA[testeracc@gmail.com]]></authoremail>
		<authorfirstname><![CDATA[tester]]></authorfirstname>
		<authorlastname><![CDATA[account]]></authorlastname>
		<slug><![CDATA[gmail-company]]></slug>
		<format><![CDATA[]]></format>
		<template><![CDATA[]]></template>
		<parent><![CDATA[0]]></parent>
		<parentslug><![CDATA[0]]></parentslug>
		<order><![CDATA[0]]></order>
		<commentstatus><![CDATA[closed]]></commentstatus>
		<pingstatus><![CDATA[closed]]></pingstatus>
		<postmodifieddate><![CDATA[2020-12-31]]></postmodifieddate>
	</node>
	<node>
		<id><![CDATA[388]]></id>
		<title><![CDATA[TEKFOR MEXICO S.A. DE C.V]]></title>
		<content><![CDATA[]]></content>
		<excerpt><![CDATA[]]></excerpt>
		<date><![CDATA[2020-12-31]]></date>
		<posttype><![CDATA[mm365_companies]]></posttype>
		<permalink><![CDATA[http://localhost/mmsdc/company/tekfor-mexico-s-a-de-c-v/]]></permalink>
		<imageurl><![CDATA[]]></imageurl>
		<imagetitle><![CDATA[]]></imagetitle>
		<imagecaption><![CDATA[]]></imagecaption>
		<imagedescription><![CDATA[]]></imagedescription>
		<imagealttext><![CDATA[]]></imagealttext>
		<imagefeatured><![CDATA[]]></imagefeatured>
		<attachmenturl><![CDATA[]]></attachmenturl>
		<categories><![CDATA[]]></categories>
		<status><![CDATA[publish]]></status>
		<authorid><![CDATA[13]]></authorid>
		<authorusername><![CDATA[tekfor]]></authorusername>
		<authoremail><![CDATA[tekfor@tekfor.in]]></authoremail>
		<authorfirstname><![CDATA[TEKFOR]]></authorfirstname>
		<authorlastname><![CDATA[MEXICO S.A. DE C.V]]></authorlastname>
		<slug><![CDATA[tekfor-mexico-s-a-de-c-v]]></slug>
		<format><![CDATA[]]></format>
		<template><![CDATA[]]></template>
		<parent><![CDATA[0]]></parent>
		<parentslug><![CDATA[0]]></parentslug>
		<order><![CDATA[0]]></order>
		<commentstatus><![CDATA[closed]]></commentstatus>
		<pingstatus><![CDATA[closed]]></pingstatus>
		<postmodifieddate><![CDATA[2020-12-31]]></postmodifieddate>
	</node>
	<node>
		<id><![CDATA[389]]></id>
		<title><![CDATA[WILLI ELBE MANUFACTURING S. DE R.L. DE C.V.]]></title>
		<content><![CDATA[]]></content>
		<excerpt><![CDATA[]]></excerpt>
		<date><![CDATA[2020-12-31]]></date>
		<posttype><![CDATA[mm365_companies]]></posttype>
		<permalink><![CDATA[http://localhost/mmsdc/company/willi-elbe-manufacturing-s-de-r-l-de-c-v/]]></permalink>
		<imageurl><![CDATA[]]></imageurl>
		<imagetitle><![CDATA[]]></imagetitle>
		<imagecaption><![CDATA[]]></imagecaption>
		<imagedescription><![CDATA[]]></imagedescription>
		<imagealttext><![CDATA[]]></imagealttext>
		<imagefeatured><![CDATA[]]></imagefeatured>
		<attachmenturl><![CDATA[]]></attachmenturl>
		<categories><![CDATA[]]></categories>
		<status><![CDATA[publish]]></status>
		<authorid><![CDATA[14]]></authorid>
		<authorusername><![CDATA[willielbe]]></authorusername>
		<authoremail><![CDATA[willielbe@willielbe.test]]></authoremail>
		<authorfirstname><![CDATA[WILLI]]></authorfirstname>
		<authorlastname><![CDATA[ELBE]]></authorlastname>
		<slug><![CDATA[willi-elbe-manufacturing-s-de-r-l-de-c-v]]></slug>
		<format><![CDATA[]]></format>
		<template><![CDATA[]]></template>
		<parent><![CDATA[0]]></parent>
		<parentslug><![CDATA[0]]></parentslug>
		<order><![CDATA[0]]></order>
		<commentstatus><![CDATA[closed]]></commentstatus>
		<pingstatus><![CDATA[closed]]></pingstatus>
		<postmodifieddate><![CDATA[2020-12-31]]></postmodifieddate>
	</node>
	<node>
		<id><![CDATA[391]]></id>
		<title><![CDATA[WÜRTH ELEKTRONIK iBE]]></title>
		<content><![CDATA[]]></content>
		<excerpt><![CDATA[]]></excerpt>
		<date><![CDATA[2020-12-31]]></date>
		<posttype><![CDATA[mm365_companies]]></posttype>
		<permalink><![CDATA[http://localhost/mmsdc/company/wurth-elektronik-ibe/]]></permalink>
		<imageurl><![CDATA[]]></imageurl>
		<imagetitle><![CDATA[]]></imagetitle>
		<imagecaption><![CDATA[]]></imagecaption>
		<imagedescription><![CDATA[]]></imagedescription>
		<imagealttext><![CDATA[]]></imagealttext>
		<imagefeatured><![CDATA[]]></imagefeatured>
		<attachmenturl><![CDATA[]]></attachmenturl>
		<categories><![CDATA[]]></categories>
		<status><![CDATA[publish]]></status>
		<authorid><![CDATA[15]]></authorid>
		<authorusername><![CDATA[wurth]]></authorusername>
		<authoremail><![CDATA[wurth@wtest.com]]></authoremail>
		<authorfirstname><![CDATA[WÜRTH]]></authorfirstname>
		<authorlastname><![CDATA[ELEKTRONIK iBE]]></authorlastname>
		<slug><![CDATA[wurth-elektronik-ibe]]></slug>
		<format><![CDATA[]]></format>
		<template><![CDATA[]]></template>
		<parent><![CDATA[0]]></parent>
		<parentslug><![CDATA[0]]></parentslug>
		<order><![CDATA[0]]></order>
		<commentstatus><![CDATA[closed]]></commentstatus>
		<pingstatus><![CDATA[closed]]></pingstatus>
		<postmodifieddate><![CDATA[2020-12-31]]></postmodifieddate>
	</node>
	<node>
		<id><![CDATA[392]]></id>
		<title><![CDATA[TQ1 DE MEXICO S.A. DE C.V.]]></title>
		<content><![CDATA[]]></content>
		<excerpt><![CDATA[]]></excerpt>
		<date><![CDATA[2021-01-04]]></date>
		<posttype><![CDATA[mm365_companies]]></posttype>
		<permalink><![CDATA[http://localhost/mmsdc/company/tq1-de-mexico-s-a-de-c-v/]]></permalink>
		<imageurl><![CDATA[]]></imageurl>
		<imagetitle><![CDATA[]]></imagetitle>
		<imagecaption><![CDATA[]]></imagecaption>
		<imagedescription><![CDATA[]]></imagedescription>
		<imagealttext><![CDATA[]]></imagealttext>
		<imagefeatured><![CDATA[]]></imagefeatured>
		<attachmenturl><![CDATA[]]></attachmenturl>
		<categories><![CDATA[]]></categories>
		<status><![CDATA[publish]]></status>
		<authorid><![CDATA[16]]></authorid>
		<authorusername><![CDATA[tq1mex]]></authorusername>
		<authoremail><![CDATA[tq1@demex.mx]]></authoremail>
		<authorfirstname><![CDATA[TQ1 DE MEXICO]]></authorfirstname>
		<authorlastname><![CDATA[S.A. DE C.V.]]></authorlastname>
		<slug><![CDATA[tq1-de-mexico-s-a-de-c-v]]></slug>
		<format><![CDATA[]]></format>
		<template><![CDATA[]]></template>
		<parent><![CDATA[0]]></parent>
		<parentslug><![CDATA[0]]></parentslug>
		<order><![CDATA[0]]></order>
		<commentstatus><![CDATA[closed]]></commentstatus>
		<pingstatus><![CDATA[closed]]></pingstatus>
		<postmodifieddate><![CDATA[2021-01-04]]></postmodifieddate>
	</node>
	<node>
		<id><![CDATA[393]]></id>
		<title><![CDATA[TEMAPLAX, S.A. DE C.V]]></title>
		<content><![CDATA[]]></content>
		<excerpt><![CDATA[]]></excerpt>
		<date><![CDATA[2021-01-04]]></date>
		<posttype><![CDATA[mm365_companies]]></posttype>
		<permalink><![CDATA[http://localhost/mmsdc/company/temaplax-s-a-de-c-v/]]></permalink>
		<imageurl><![CDATA[]]></imageurl>
		<imagetitle><![CDATA[]]></imagetitle>
		<imagecaption><![CDATA[]]></imagecaption>
		<imagedescription><![CDATA[]]></imagedescription>
		<imagealttext><![CDATA[]]></imagealttext>
		<imagefeatured><![CDATA[]]></imagefeatured>
		<attachmenturl><![CDATA[]]></attachmenturl>
		<categories><![CDATA[]]></categories>
		<status><![CDATA[publish]]></status>
		<authorid><![CDATA[17]]></authorid>
		<authorusername><![CDATA[temaplax]]></authorusername>
		<authoremail><![CDATA[temaplax@temaplax.mx]]></authoremail>
		<authorfirstname><![CDATA[TEMAPLAX]]></authorfirstname>
		<authorlastname><![CDATA[S.A. DE C.V]]></authorlastname>
		<slug><![CDATA[temaplax-s-a-de-c-v]]></slug>
		<format><![CDATA[]]></format>
		<template><![CDATA[]]></template>
		<parent><![CDATA[0]]></parent>
		<parentslug><![CDATA[0]]></parentslug>
		<order><![CDATA[0]]></order>
		<commentstatus><![CDATA[closed]]></commentstatus>
		<pingstatus><![CDATA[closed]]></pingstatus>
		<postmodifieddate><![CDATA[2021-01-04]]></postmodifieddate>
	</node>
	<node>
		<id><![CDATA[395]]></id>
		<title><![CDATA[TOPURA FASTENER DE MEXICO, S.A. DE C.V.]]></title>
		<content><![CDATA[]]></content>
		<excerpt><![CDATA[]]></excerpt>
		<date><![CDATA[2021-01-04]]></date>
		<posttype><![CDATA[mm365_companies]]></posttype>
		<permalink><![CDATA[http://localhost/mmsdc/company/topura-fastener-de-mexico-s-a-de-c-v/]]></permalink>
		<imageurl><![CDATA[]]></imageurl>
		<imagetitle><![CDATA[]]></imagetitle>
		<imagecaption><![CDATA[]]></imagecaption>
		<imagedescription><![CDATA[]]></imagedescription>
		<imagealttext><![CDATA[]]></imagealttext>
		<imagefeatured><![CDATA[]]></imagefeatured>
		<attachmenturl><![CDATA[]]></attachmenturl>
		<categories><![CDATA[]]></categories>
		<status><![CDATA[publish]]></status>
		<authorid><![CDATA[18]]></authorid>
		<authorusername><![CDATA[TOPURA]]></authorusername>
		<authoremail><![CDATA[TOPURA@faste.com]]></authoremail>
		<authorfirstname><![CDATA[TOPURA FASTENER]]></authorfirstname>
		<authorlastname><![CDATA[DE MEXICO, S.A. DE C.V.]]></authorlastname>
		<slug><![CDATA[topura-fastener-de-mexico-s-a-de-c-v]]></slug>
		<format><![CDATA[]]></format>
		<template><![CDATA[]]></template>
		<parent><![CDATA[0]]></parent>
		<parentslug><![CDATA[0]]></parentslug>
		<order><![CDATA[0]]></order>
		<commentstatus><![CDATA[closed]]></commentstatus>
		<pingstatus><![CDATA[closed]]></pingstatus>
		<postmodifieddate><![CDATA[2021-01-04]]></postmodifieddate>
	</node>
	<node>
		<id><![CDATA[407]]></id>
		<title><![CDATA[Testing Company]]></title>
		<content><![CDATA[]]></content>
		<excerpt><![CDATA[]]></excerpt>
		<date><![CDATA[1970-01-01]]></date>
		<posttype><![CDATA[mm365_companies]]></posttype>
		<permalink><![CDATA[http://localhost/mmsdc/?post_type=mm365_companies&p=407]]></permalink>
		<imageurl><![CDATA[]]></imageurl>
		<imagetitle><![CDATA[]]></imagetitle>
		<imagecaption><![CDATA[]]></imagecaption>
		<imagedescription><![CDATA[]]></imagedescription>
		<imagealttext><![CDATA[]]></imagealttext>
		<imagefeatured><![CDATA[]]></imagefeatured>
		<attachmenturl><![CDATA[]]></attachmenturl>
		<categories><![CDATA[]]></categories>
		<status><![CDATA[draft]]></status>
		<authorid><![CDATA[20]]></authorid>
		<authorusername><![CDATA[magna_john_de]]></authorusername>
		<authoremail><![CDATA[sampleusessr@test.com]]></authoremail>
		<authorfirstname><![CDATA[das]]></authorfirstname>
		<authorlastname><![CDATA[Doe]]></authorlastname>
		<slug><![CDATA[]]></slug>
		<format><![CDATA[]]></format>
		<template><![CDATA[]]></template>
		<parent><![CDATA[0]]></parent>
		<parentslug><![CDATA[0]]></parentslug>
		<order><![CDATA[0]]></order>
		<commentstatus><![CDATA[closed]]></commentstatus>
		<pingstatus><![CDATA[closed]]></pingstatus>
		<postmodifieddate><![CDATA[2021-01-05]]></postmodifieddate>
	</node>
	<node>
		<id><![CDATA[408]]></id>
		<title><![CDATA[dfdfdfdf fdg inc.]]></title>
		<content><![CDATA[]]></content>
		<excerpt><![CDATA[]]></excerpt>
		<date><![CDATA[2021-01-07]]></date>
		<posttype><![CDATA[mm365_companies]]></posttype>
		<permalink><![CDATA[http://localhost/mmsdc/company/dfdf/]]></permalink>
		<imageurl><![CDATA[]]></imageurl>
		<imagetitle><![CDATA[]]></imagetitle>
		<imagecaption><![CDATA[]]></imagecaption>
		<imagedescription><![CDATA[]]></imagedescription>
		<imagealttext><![CDATA[]]></imagealttext>
		<imagefeatured><![CDATA[]]></imagefeatured>
		<attachmenturl><![CDATA[]]></attachmenturl>
		<categories><![CDATA[]]></categories>
		<status><![CDATA[publish]]></status>
		<authorid><![CDATA[21]]></authorid>
		<authorusername><![CDATA[dummy11]]></authorusername>
		<authoremail><![CDATA[dummy@gmail.com]]></authoremail>
		<authorfirstname><![CDATA[dummy11]]></authorfirstname>
		<authorlastname><![CDATA[dummy]]></authorlastname>
		<slug><![CDATA[dfdf]]></slug>
		<format><![CDATA[]]></format>
		<template><![CDATA[]]></template>
		<parent><![CDATA[0]]></parent>
		<parentslug><![CDATA[0]]></parentslug>
		<order><![CDATA[0]]></order>
		<commentstatus><![CDATA[closed]]></commentstatus>
		<pingstatus><![CDATA[closed]]></pingstatus>
		<postmodifieddate><![CDATA[2021-01-07]]></postmodifieddate>
	</node>
</data>
